Comprehensive_RAG_Evaluation_Metrics/__init__.py
Comprehensive_RAG_Evaluation_Metrics/eval.py
Comprehensive_RAG_Evaluation_Metrics/test_evaluator.py
Comprehensive_RAG_Evaluation_Metrics-0.12.0.dist-info/LICENSE.txt
Comprehensive_RAG_Evaluation_Metrics-0.12.0.dist-info/METADATA
Comprehensive_RAG_Evaluation_Metrics-0.12.0.dist-info/WHEEL
Comprehensive_RAG_Evaluation_Metrics-0.12.0.dist-info/top_level.txt
Comprehensive_RAG_Evaluation_Metrics-0.12.0.dist-info/RECORD
