Metadata-Version: 2.1
Name: Comprehensive_RAG_Evaluation_Metrics
Version: 0.12.0
Summary: This library provides a comprehensive suite of metrics to evaluate the performance of Retrieval-Augmented Generation (RAG) systems. RAG systems, which combine information retrieval with text generation, present unique evaluation challenges beyond those found in standard language generation tasks
Home-page: https://github.com/beekash222/RAG_EVAL
Author: Beekash Mohanty
Author-email: beekashmohanty222@gmail.com
Classifier: Programming Language :: Python :: 3
Classifier: License :: OSI Approved :: MIT License
Classifier: Operating System :: OS Independent
Requires-Python: >=3.9
License-File: LICENSE.txt
Requires-Dist: torch
Requires-Dist: sacrebleu
Requires-Dist: rouge-score
Requires-Dist: bert-score
Requires-Dist: transformers
Requires-Dist: nltk
Requires-Dist: textblob
Requires-Dist: textstat
Requires-Dist: tabulate
